angle_tompy/__init__.py
angle_tompy/angle.py
angle_tompy/angle_decimal.py
angle_tompy/exceptions.py
angle_tompy-2025.10.8.23.47.dist-info/METADATA
angle_tompy-2025.10.8.23.47.dist-info/WHEEL
angle_tompy-2025.10.8.23.47.dist-info/RECORD
