Metadata-Version: 2.4
Name: angle-tompy
Version: 2025.10.8.23.47
Summary: Angles for tompy projects
Author: tompy
Classifier: Development Status :: 3 - Alpha
Classifier: Intended Audience :: Developers
Classifier: License :: OSI Approved :: GNU General Public License v3 (GPLv3)
Classifier: Operating System :: OS Independent
Classifier: Programming Language :: Python :: 3.9
Requires-Python: >=3.9
Requires-Dist: iterable-tompy>=2025.5.19.19.1
Requires-Dist: py-cdll>=2025.05.06.10.15
Requires-Dist: sympy>=1.14.0
